README.txt
setup.cfg
setup.py
collective/__init__.py
collective.duplicateaction.egg-info/PKG-INFO
collective.duplicateaction.egg-info/SOURCES.txt
collective.duplicateaction.egg-info/dependency_links.txt
collective.duplicateaction.egg-info/entry_points.txt
collective.duplicateaction.egg-info/namespace_packages.txt
collective.duplicateaction.egg-info/not-zip-safe
collective.duplicateaction.egg-info/paster_plugins.txt
collective.duplicateaction.egg-info/requires.txt
collective.duplicateaction.egg-info/top_level.txt
collective/duplicateaction/__init__.py
collective/duplicateaction/browser.py
collective/duplicateaction/configure.zcml
collective/duplicateaction/tests.py
collective/duplicateaction/update_i18n.sh
collective/duplicateaction/locales/collective.duplicateaction.pot
collective/duplicateaction/locales/cs/LC_MESSAGES/collective.duplicateaction.po
collective/duplicateaction/locales/en/LC_MESSAGES/collective.duplicateaction.po
collective/duplicateaction/profiles/default/actions.xml
collective/duplicateaction/profiles/default/browserlayer.xml
collective/duplicateaction/profiles/default/metadata.xml
docs/HISTORY.txt
docs/INSTALL.txt
docs/LICENSE.GPL
docs/LICENSE.txt