Metadata-Version: 1.0
Name: collective.duplicateaction
Version: 1.0
Summary: Adds additional action to content actions menu for duplicating content.
Home-page: http://github.com/collective/collective.duplicateaction
Author: Lukas Zdych
Author-email: lukas.zdych@gmail.com
License: GPL
Keywords: plone contentaction duplicate
Platform: UNKNOWN
Classifier: Framework :: Plone
Classifier: Programming Language :: Python
